{
	"data" : [
		{"id":50,	"lat":43.095080,	"lon":-77.601662,"dir":"N",	"type":"guid", "value":"I390 North Airport Greece"},
		{"id":51,	"lat":43.095080,	"lon":-77.601662,"dir":"N",	"type":"guid",	"value":"Exit 15"},
		{"id":52,	"lat":43.095080,	"lon":-77.601662,"dir":"N",	"type":"guid",	"value":"I590 North Downtown Rochester Irondequoit 3/4 Mile Exit Only"},
		{"id":53,	"lat":43.095080,	"lon":-77.601662,"dir":"N",	"type":"guid",	"value":"Brighton Henrietta Townline Road"},
		{"id":54,	"lat":43.095080,	"lon":-77.601662,"dir":"N",	"type":"guid",	"value":"Town of Brighton"},
		
		{"id":55,	"lat":43.096028,	"lon":-77.601339,"dir":"N",	"type":"spdl", "value":"55"},
		
		{"id":56,	"lat":43.097834,	"lon":-77.600763,"dir":"N",	"type":"guid", "value":"Emergency Detour E"},
		{"id":57,	"lat":43.097834,	"lon":-77.600763,"dir":"N",	"type":"guid", "value":"Emergency Detour F"},

		{"id":58,	"lat":43.098468,	"lon":-77.600572,"dir":"N",	"type":"spdl", "value":"55"},

		{"id":59,	"lat":43.103743,	"lon":-77.600179,"dir":"N",	"type":"guid", "value":"Emergency Detour E"},
		{"id":510,	"lat":43.103743,	"lon":-77.600179,"dir":"N",	"type":"guid", "value":"I390 North Airport Greece"},
		{"id":511,	"lat":43.103743,	"lon":-77.600179,"dir":"N",	"type":"guid",	"value":"Exit 15"},
		{"id":512,	"lat":43.103743,	"lon":-77.600179,"dir":"N",	"type":"guid",	"value":"I590 North Downtown Rochester 1/4 Mile Exit Only"},
		{"id":513,	"lat":43.103743,	"lon":-77.600179,"dir":"N",	"type":"guid", "value":"Emergency Detour F"},
	
		{"id":514,	"lat":43.106034,	"lon":-77.600132,"dir":"N",	"type":"guid", "value":"Emergency Detour E"},
		{"id":515,	"lat":43.106034,	"lon":-77.600132,"dir":"N",	"type":"guid", "value":"I390 North Airport Greece Ramp 50 MPH"},
		{"id":516,	"lat":43.106034,	"lon":-77.600132,"dir":"N",	"type":"guid",	"value":"Exit 15"},
		{"id":517,	"lat":43.106034,	"lon":-77.600132,"dir":"N",	"type":"guid",	"value":"I590 North Downtown Rochester"},
		{"id":518,	"lat":43.106034,	"lon":-77.600132,"dir":"N",	"type":"guid", "value":"Emergency Detour F"},
	
		{"id":519,	"lat":43.107788,	"lon":-77.599702,"dir":"N",	"type":"guid", "value":"Exit 15"},

		{"id":520,	"lat":43.110104,	"lon":-77.599862,"dir":"N",	"type":"guid", "value":"Exits 16 B-A"},
		{"id":521,	"lat":43.110104,	"lon":-77.599862,"dir":"N",	"type":"guid", "value":"15A East Henrietta Road 15 West Henrietta Road 3/4 Mile"},

		{"id":522,	"lat":43.110614,	"lon":-77.605903,"dir":"N",	"type":"guid", "value":"MCC U of R U of R Medical Center Exit 16A"},

		{"id":523,	"lat":43.109695,	"lon":-77.608753,"dir":"N",	"type":"guid", "value":"Exits 16 B-A"},
		{"id":524,	"lat":43.109695,	"lon":-77.608753,"dir":"N",	"type":"guid", "value":"15A East Henrietta Road 15 West Henrietta Road Exit Only"},

		{"id":525,	"lat":43.109084,	"lon":-77.610191,"dir":"N",	"type":"spdl", "value":"55"},

		{"id":526,	"lat":43.108285,	"lon":-77.612230,"dir":"N",	"type":"guid", "value":"Exit 16A"},
		{"id":527,	"lat":43.108285,	"lon":-77.612230,"dir":"N",	"type":"guid", "value":"15A South East Henrietta Road 15 West Henrietta Road Exit Only"},

		{"id":528,	"lat":43.108285,	"lon":-77.612230,"dir":"N",	"type":"guid", "value":"Exit 16B"},
		{"id":529,	"lat":43.108285,	"lon":-77.612230,"dir":"N",	"type":"guid", "value":"15A North East Henrietta Road Rochester"},

		{"id":529,	"lat":43.108264,	"lon":-77.612248,"dir":"N",	"type":"guid", "value":"Exit 16B"},

		{"id":530,	"lat":43.1079036,	"lon":-77.6142665,"dir":"N", "type":"guid", "value":"Exit 16A"},
		{"id":531,	"lat":43.1079036,	"lon":-77.6142665,"dir":"N", "type":"guid", "value":"U of R Medical Center MCC"},
		
		{"id":532,	"lat":43.1079857,	"lon":-77.6157063,"dir":"N",	"type":"guid", "value":"Exit 16A"},
		{"id":533,	"lat":43.1079857,	"lon":-77.6157063,"dir":"N",	"type":"guid", "value":"15A South East Henrietta Road 15 West Henrietta Road Exit Only"},
		{"id":534,	"lat":43.1079857,	"lon":-77.6157063,"dir":"N",	"type":"guid",	"value":"NY 15A Brighton"},

		{"id":535,	"lat":43.108463,	"lon":-77.617467,"dir":"N",	"type":"guid", "value":"15 U of R Medical Center"},
		{"id":536,	"lat":43.108463,	"lon":-77.617467,"dir":"N",	"type":"guid",	"value":"South 15A MCC"},
		
		{"id":537,	"lat":43.1160155,	"lon":-77.6325506,"dir":"N",	"type":"guid",	"value":"Kendrick Rd"},
		
		{"id":538,	"lat":43.1191933,	"lon":-77.6388798,"dir":"N",	"type":"guid", "value":"Exit 17"},
		{"id":539,	"lat":43.1191933,	"lon":-77.6388798,"dir":"N",	"type":"guid", "value":"383 Scottsville Rd RIT 1/2 Mile"}
		
	]
}
